spacypdfreader/__init__.py
spacypdfreader/_utils.py
spacypdfreader/console.py
spacypdfreader/spacypdfreader.py
spacypdfreader/parsers/__init__.py
spacypdfreader/parsers/pdfminer.py
spacypdfreader/parsers/pytesseract.py
spacypdfreader-0.3.2.dist-info/METADATA
spacypdfreader-0.3.2.dist-info/WHEEL
spacypdfreader-0.3.2.dist-info/licenses/LICENSE
spacypdfreader-0.3.2.dist-info/RECORD
