Metadata-Version: 2.3
Name: spacypdfreader
Version: 0.3.2
Summary: A PDF to text extraction pipeline component for spaCy.
Project-URL: Homepage, https://samedwardes.github.io/spacypdfreader
Project-URL: Documentation, https://samedwardes.github.io/spacypdfreader
Project-URL: Repository, https://github.com/SamEdwardes/spaCyPDFreader.git
Project-URL: Issues, https://github.com/SamEdwardes/spaCyPDFreader/issues
Project-URL: Changelog, https://github.com/SamEdwardes/spacypdfreader/blob/main/docs/changelog.md
Maintainer-email: Sam Edwardes <edwardes.s@gmail.com>
License-Expression: MIT
License-File: LICENSE
Keywords: nlp,pdf,pdfs,python,spacy
Requires-Python: >=3.9
Requires-Dist: pdfminer-six>=20240706
Requires-Dist: rich>=13.9.2
Requires-Dist: spacy>=3.8.2
Provides-Extra: pytesseract
Requires-Dist: pdf2image>=1.17.0; extra == 'pytesseract'
Requires-Dist: pillow>=10.4.0; extra == 'pytesseract'
Requires-Dist: pytesseract>=0.3.13; extra == 'pytesseract'
